{
  "_fv": 18,
  "_type": "gui",
  "definition": {
    "type": 1,
    "width": 176,
    "height": 134,
    "inventoryOffsetX": 0,
    "inventoryOffsetY": -14,
    "renderBgLayer": true,
    "doesPauseGame": false,
    "components": [
      {
        "type": "label",
        "data": {
          "text": "Dream Holder",
          "color": {
            "value": -16777216,
            "falpha": 0.0
          },
          "name": "Dream Holder",
          "x": 131,
          "y": 59
        }
      },
      {
        "type": "inputslot",
        "data": {
          "inputLimit": {
            "value": "CUSTOM:DreamWood"
          },
          "id": 0,
          "disableStackInteraction": false,
          "dropItemsWhenNotBound": false,
          "name": "Slot #0",
          "x": 168,
          "y": 72
        }
      },
      {
        "type": "inputslot",
        "data": {
          "inputLimit": {
            "value": "CUSTOM:DreamWood"
          },
          "id": 1,
          "disableStackInteraction": false,
          "dropItemsWhenNotBound": false,
          "name": "Slot #1",
          "x": 186,
          "y": 72
        }
      },
      {
        "type": "inputslot",
        "data": {
          "inputLimit": {
            "value": "CUSTOM:DreamWood"
          },
          "id": 2,
          "disableStackInteraction": false,
          "dropItemsWhenNotBound": false,
          "name": "Slot #2",
          "x": 204,
          "y": 72
        }
      },
      {
        "type": "inputslot",
        "data": {
          "inputLimit": {
            "value": "CUSTOM:DreamWood"
          },
          "id": 3,
          "disableStackInteraction": false,
          "dropItemsWhenNotBound": false,
          "name": "Slot #3",
          "x": 222,
          "y": 72
        }
      },
      {
        "type": "inputslot",
        "data": {
          "inputLimit": {
            "value": "CUSTOM:DreamWood"
          },
          "id": 4,
          "disableStackInteraction": false,
          "dropItemsWhenNotBound": false,
          "name": "Slot #4",
          "x": 240,
          "y": 72
        }
      }
    ]
  }
}